LICENSE.txt
MANIFEST.in
README.rst
setup.py
picamera/__init__.py
picamera/array.py
picamera/bcm_host.py
picamera/camera.py
picamera/color.py
picamera/encoders.py
picamera/exc.py
picamera/frames.py
picamera/mmal.py
picamera/mmalobj.py
picamera/renderers.py
picamera/streams.py
picamera.egg-info/PKG-INFO
picamera.egg-info/SOURCES.txt
picamera.egg-info/dependency_links.txt
picamera.egg-info/pbr.json
picamera.egg-info/requires.txt
picamera.egg-info/top_level.txt