Metadata-Version: 1.1
Name: picamera
Version: 1.11
Summary: A pure Python interface for the Raspberry Pi camera module.
Home-page: http://picamera.readthedocs.io/
Author: Dave Jones
Author-email: dave@waveform.org.uk
License: BSD License
Keywords: raspberrypi,camera
Platform: ALL
Classifier: Development Status :: 5 - Production/Stable
Classifier: Environment :: Console
Classifier: Intended Audience :: Developers
Classifier: License :: OSI Approved :: BSD License
Classifier: Operating System :: POSIX :: Linux
Classifier: Programming Language :: Python :: 2.7
Classifier: Programming Language :: Python :: 3.2
Classifier: Programming Language :: Python :: 3.3
Classifier: Topic :: Multimedia :: Graphics :: Capture :: Digital Camera
